BeginnersbookJstlJiaochengChuyiFix1/README.md
BeginnersbookJstlJiaochengChuyiFix1/__init__.py
BeginnersbookJstlJiaochengChuyiFix1/__main__.py
BeginnersbookJstlJiaochengChuyiFix1/file.epub
BeginnersbookJstlJiaochengChuyiFix1/index.html
BeginnersbookJstlJiaochengChuyiFix1/css/__init__.py
BeginnersbookJstlJiaochengChuyiFix1/css/annotations.css
BeginnersbookJstlJiaochengChuyiFix1/css/main.css
BeginnersbookJstlJiaochengChuyiFix1/css/normalize.css
BeginnersbookJstlJiaochengChuyiFix1/css/popup.css
BeginnersbookJstlJiaochengChuyiFix1/font/__init__.py
BeginnersbookJstlJiaochengChuyiFix1/font/fontello.eot
BeginnersbookJstlJiaochengChuyiFix1/font/fontello.svg
BeginnersbookJstlJiaochengChuyiFix1/font/fontello.ttf
BeginnersbookJstlJiaochengChuyiFix1/font/fontello.woff
BeginnersbookJstlJiaochengChuyiFix1/img/__init__.py
BeginnersbookJstlJiaochengChuyiFix1/img/annotator-glyph-sprite.png
BeginnersbookJstlJiaochengChuyiFix1/img/annotator-icon-sprite.png
BeginnersbookJstlJiaochengChuyiFix1/img/apple-touch-icon.png
BeginnersbookJstlJiaochengChuyiFix1/img/cancelfullscreen.png
BeginnersbookJstlJiaochengChuyiFix1/img/close.png
BeginnersbookJstlJiaochengChuyiFix1/img/fullscreen.png
BeginnersbookJstlJiaochengChuyiFix1/img/loader.gif
BeginnersbookJstlJiaochengChuyiFix1/img/menu-icon.png
BeginnersbookJstlJiaochengChuyiFix1/img/save.png
BeginnersbookJstlJiaochengChuyiFix1/img/saved.png
BeginnersbookJstlJiaochengChuyiFix1/img/settings-s.png
BeginnersbookJstlJiaochengChuyiFix1/img/settings.png
BeginnersbookJstlJiaochengChuyiFix1/img/star.png
BeginnersbookJstlJiaochengChuyiFix1/js/__init__.py
BeginnersbookJstlJiaochengChuyiFix1/js/epub.js
BeginnersbookJstlJiaochengChuyiFix1/js/epub.min.js
BeginnersbookJstlJiaochengChuyiFix1/js/epub.min.map
BeginnersbookJstlJiaochengChuyiFix1/js/hooks.min.js
BeginnersbookJstlJiaochengChuyiFix1/js/hooks.min.map
BeginnersbookJstlJiaochengChuyiFix1/js/reader.js
BeginnersbookJstlJiaochengChuyiFix1/js/reader.js.map
BeginnersbookJstlJiaochengChuyiFix1/js/reader.min.js
beginnersbook_jstl_jiaocheng_chuyi_fix1-2025.3.24.0.dist-info/METADATA
beginnersbook_jstl_jiaocheng_chuyi_fix1-2025.3.24.0.dist-info/WHEEL
beginnersbook_jstl_jiaocheng_chuyi_fix1-2025.3.24.0.dist-info/entry_points.txt
beginnersbook_jstl_jiaocheng_chuyi_fix1-2025.3.24.0.dist-info/top_level.txt
beginnersbook_jstl_jiaocheng_chuyi_fix1-2025.3.24.0.dist-info/RECORD
